rlane_sumdups-1.0.3.dist-info/METADATA
rlane_sumdups-1.0.3.dist-info/WHEEL
rlane_sumdups-1.0.3.dist-info/entry_points.txt
rlane_sumdups-1.0.3.dist-info/licenses/LICENSE
sumdups/__init__.py
sumdups/__main__.py
sumdups/cli.py
sumdups/subfile.py
rlane_sumdups-1.0.3.dist-info/RECORD
