Metadata-Version: 2.1
Name: rlane-sumdups
Version: 1.0.3
Summary: checksum/duplicates, yada...
Keywords: checksum,duplicates
Author-Email: Russel Lane <russel@rlane.com>
License: MIT
Classifier: Development Status :: 4 - Beta
Classifier: Intended Audience :: End Users/Desktop
Classifier: License :: OSI Approved :: MIT License
Classifier: Programming Language :: Python :: 3
Project-URL: Homepage, https://github.com/russellane/sumdups
Requires-Python: >=3.10
Requires-Dist: argcomplete>=3.5.1
Requires-Dist: libmagic>=1.0
Requires-Dist: loguru>=0.7.2
Requires-Dist: pyexiftool>=0.5.6
Requires-Dist: python-dateutil>=2.9.0.post0
Requires-Dist: python-magic>=0.4.27
Requires-Dist: rlane-libcli>=1.0.8
Requires-Dist: rlane-libfile>=1.0.2
Requires-Dist: rlane-pathtree>=1.0.2
Requires-Dist: termcolor>=2.5.0
Requires-Dist: xdg>=6.0.0
